lakeridersalert/__init__.py
lakeridersalert/__main__.py
lakeridersalert/main.py
lakeridersalert/constants/__init__.py
lakeridersalert/helpers/__init__.py
lakeridersalert/helpers/calendar_entries.py
lakeridersalert/helpers/run.py
lakeridersalert/helpers/telegram_bot.py
lakeridersalert/helpers/web.py
lakeriders_alert-0.1.2.dist-info/LICENSE.txt
lakeriders_alert-0.1.2.dist-info/METADATA
lakeriders_alert-0.1.2.dist-info/WHEEL
lakeriders_alert-0.1.2.dist-info/entry_points.txt
lakeriders_alert-0.1.2.dist-info/top_level.txt
lakeriders_alert-0.1.2.dist-info/RECORD
