Metadata-Version: 2.1
Name: lakeriders-alert
Version: 0.1.2
Summary: Get a Telegram message whenever a wakeboard session with the LakeRiders club becomes available
Author-email: Eduardo Conde Pena <econdepe@pm.me>
Project-URL: Homepage, https://github.com/econdepe/LakeRidersAlert
Project-URL: Issues, https://github.com/econdepe/LakeRidersAlert/issues
Requires-Python: >=3.8
License-File: LICENSE.txt
Requires-Dist: click >=8.1
Requires-Dist: requests >=2.32
Provides-Extra: dev
Requires-Dist: ruff >=0.6 ; extra == 'dev'
Requires-Dist: pre-commit >=3.8 ; extra == 'dev'
Requires-Dist: PyYAML >=6.0 ; extra == 'dev'
